covid19/PlotSouthAsia.py
covid19/PlotTCRAndCTR.py
covid19/PlotVaxBreakdown.py
covid19/PlotVaxBreakdownDaily.py
covid19/PlotVaxProfileImage.py
covid19/PlotVaxProjection.py
covid19/PlotVaxSummary.py
covid19/PlotWorld.py
covid19/__init__.py
covid19/_utils.py
covid19/covid_data.py
covid19/epid.py
covid19/lk_data.py
covid19/plots_lk.py
covid19/tweet_lk_update.py
covid19/tweet_sa_update.py
covid19/tweet_tcr_update.py
covid19/tweet_vax_update.py
covid19/tweet_world_top_vax.py
covid19/tweet_world_update.py
covid19/upload_data.py
covid19/upload_data_back_pop.py
covid19_nuuuwan-1.0.2.dist-info/LICENCE
covid19_nuuuwan-1.0.2.dist-info/METADATA
covid19_nuuuwan-1.0.2.dist-info/WHEEL
covid19_nuuuwan-1.0.2.dist-info/top_level.txt
covid19_nuuuwan-1.0.2.dist-info/RECORD
